luctools/analyse.py
luctools-0.2.dist-info/LICENSE
luctools-0.2.dist-info/METADATA
luctools-0.2.dist-info/WHEEL
luctools-0.2.dist-info/top_level.txt
luctools-0.2.dist-info/RECORD
