Metadata-Version: 2.1
Name: luctools
Version: 0.2
Summary: Detrending, period/phase prediction and plotting of luciferase time series
Home-page: https://github.com/aleccrowell/luctools
Author: Alec Crowell
Author-email: alexander.m.crowell@gmail.com
License: BSD-3
Download-URL: https://github.com/aleccrowell/luctools/releases/tag/v0.2
Keywords: circadian,luciferase
Platform: UNKNOWN
Requires-Dist: numpy
Requires-Dist: pandas
Requires-Dist: scipy
Requires-Dist: matplotlib
Requires-Dist: seaborn
Requires-Dist: peakutils
